smallpower/color_table_generator.js
smallpower/conf.py
smallpower/fitSmallPowerData.py
smallpower/parameters_conf.default.py
smallpower/parameters_conf.py
smallpower/smallPower.py
smallpower/confFiles/ALPHA - BD Instrum XL_V2.47.xlsm
smallpower/confFiles/colors_tags.html
smallpower/confFiles/devices_HUB_v1.ods
smallpower/confFiles/my_cert.pem
smallpower/confFiles/my_private_key.pem
smallpower/confFiles/smallpower_conf.pkl
smallpower/confFiles/smallpower_configfiles.ods
smallpower/confFiles/versionnage_tags.ods
smallpower/confFiles/pictures/angrypainter.gif
smallpower/confFiles/pictures/logo_sylfen.png
smallpower/confFiles/pictures/peintrepalette.jpeg
smallPower-6.4.1.dist-info/METADATA
smallPower-6.4.1.dist-info/WHEEL
smallPower-6.4.1.dist-info/top_level.txt
smallPower-6.4.1.dist-info/RECORD
