Metadata-Version: 2.1
Name: smallPower
Version: 6.4.1
Summary: source codes and config Files to monitor small power data
Home-page: UNKNOWN
Author: Dorian Drevon
Author-email: drevondorian@gmail.com
License: UNKNOWN
Platform: UNKNOWN
Classifier: Programming Language :: Python :: 3
Classifier: License :: OSI Approved :: MIT License
Classifier: Operating System :: OS Independent
Requires-Python: >=3.8
Requires-Dist: dorianUtils (==6.4.1)
